{
  "project_info": {
    "project_number": "530948644152",
    "project_id": "wetoo-7beb7",
    "storage_bucket": "wetoo-7beb7.appspot.com"
  },
  "client": [
    {
      "client_info": {
        "mobilesdk_app_id": "1:530948644152:android:b6749fe7e470a7eeb7b5cd",
        "android_client_info": {
          "package_name": "com.company.WeToo"
        }
      },
      "oauth_client": [
        {
          "client_id": "530948644152-robetl5d285gon6toq0s8vvmmnlth1kv.apps.googleusercontent.com",
          "client_type": 3
        }
      ],
      "api_key": [
        {
          "current_key": "AIzaSyC_aMRLwV7MQLGY8mZPJ_IhjoEZeUeevm4"
        }
      ],
      "services": {
        "appinvite_service": {
          "other_platform_oauth_client": [
            {
              "client_id": "530948644152-robetl5d285gon6toq0s8vvmmnlth1kv.apps.googleusercontent.com",
              "client_type": 3
            }
          ]
        }
      }
    }
  ],
  "configuration_version": "1"
}